djcms_custom_menu/__init__.py
djcms_custom_menu/admin.py
djcms_custom_menu/apps.py
djcms_custom_menu/cache.py
djcms_custom_menu/models.py
djcms_custom_menu/nodes.py
djcms_custom_menu/settings.py
djcms_custom_menu/signals.py
djcms_custom_menu/static/djcmscustommenu/css/admin.css
djcms_custom_menu/static/djcmscustommenu/css/admin.min.css
djcms_custom_menu/static/djcmscustommenu/ext/jquery-3.3.1.min.js
djcms_custom_menu/static/djcmscustommenu/ext/jquery-ui.min.js
djcms_custom_menu/static/djcmscustommenu/ext/jquery.nestable.js
djcms_custom_menu/static/djcmscustommenu/ext/jquery.nestable.min.css
djcms_custom_menu/static/djcmscustommenu/ext/jquery.nestable.min.js
djcms_custom_menu/templates/djcms_custom_menu/admin_select.html
djcms_custom_menu/templates/djcms_custom_menu/available_item.html
djcms_custom_menu/templates/djcms_custom_menu/change_form.html
djcms_custom_menu/templates/djcms_custom_menu/fieldset.html
djcms_custom_menu/templates/djcms_custom_menu/menu_item.html
djcms_custom_menu/templates/djcms_custom_menu/nestable_item.html
djcms_custom_menu/templates/snippets/cms_named_menu.html
djcms_custom_menu-1.0.1.dist-info/LICENSE
djcms_custom_menu-1.0.1.dist-info/METADATA
djcms_custom_menu-1.0.1.dist-info/WHEEL
djcms_custom_menu-1.0.1.dist-info/top_level.txt
djcms_custom_menu-1.0.1.dist-info/RECORD
