Metadata-Version: 2.1
Name: djcms-custom-menu
Version: 1.0.1
Summary: An extension for Django CMS that allows you to create and edit multiple menus like Wordpress. This is compatible for Python 3.6, Django 2.1.9, django-cms 3.6.0
Home-page: https://github.com/imbipul/djcms-custom-menu
Author: Abdullah Al Arafat Bipul
Author-email: imbipul9@gmail.com
License: UNKNOWN
Platform: UNKNOWN
Classifier: Environment :: Web Environment
Classifier: Intended Audience :: Developers
Classifier: License :: OSI Approved :: MIT License
Classifier: Operating System :: OS Independent
Classifier: Framework :: Django
Classifier: Framework :: Django :: 2.1
Classifier: Programming Language :: Python
Classifier: Programming Language :: Python :: 3.6
Classifier: Programming Language :: Python :: 3.7
Classifier: Topic :: Internet :: WWW/HTTP
Classifier: Topic :: Internet :: WWW/HTTP :: Dynamic Content
Requires-Dist: Django (>=2.1.9)
Requires-Dist: django-classy-tags
Requires-Dist: django-cms (>=3.6.0)
Requires-Dist: jsonfield (>=1.0.0)
Requires-Dist: django-autoslug (>=1.7.2)
